UcbCs294ShenduQianghuaXuexiZhongwenBijiXietian/README.md
UcbCs294ShenduQianghuaXuexiZhongwenBijiXietian/__init__.py
UcbCs294ShenduQianghuaXuexiZhongwenBijiXietian/__main__.py
UcbCs294ShenduQianghuaXuexiZhongwenBijiXietian/file.epub
UcbCs294ShenduQianghuaXuexiZhongwenBijiXietian/index.html
UcbCs294ShenduQianghuaXuexiZhongwenBijiXietian/css/__init__.py
UcbCs294ShenduQianghuaXuexiZhongwenBijiXietian/css/annotations.css
UcbCs294ShenduQianghuaXuexiZhongwenBijiXietian/css/main.css
UcbCs294ShenduQianghuaXuexiZhongwenBijiXietian/css/normalize.css
UcbCs294ShenduQianghuaXuexiZhongwenBijiXietian/css/popup.css
UcbCs294ShenduQianghuaXuexiZhongwenBijiXietian/font/__init__.py
UcbCs294ShenduQianghuaXuexiZhongwenBijiXietian/font/fontello.eot
UcbCs294ShenduQianghuaXuexiZhongwenBijiXietian/font/fontello.svg
UcbCs294ShenduQianghuaXuexiZhongwenBijiXietian/font/fontello.ttf
UcbCs294ShenduQianghuaXuexiZhongwenBijiXietian/font/fontello.woff
UcbCs294ShenduQianghuaXuexiZhongwenBijiXietian/img/__init__.py
UcbCs294ShenduQianghuaXuexiZhongwenBijiXietian/img/annotator-glyph-sprite.png
UcbCs294ShenduQianghuaXuexiZhongwenBijiXietian/img/annotator-icon-sprite.png
UcbCs294ShenduQianghuaXuexiZhongwenBijiXietian/img/apple-touch-icon.png
UcbCs294ShenduQianghuaXuexiZhongwenBijiXietian/img/cancelfullscreen.png
UcbCs294ShenduQianghuaXuexiZhongwenBijiXietian/img/close.png
UcbCs294ShenduQianghuaXuexiZhongwenBijiXietian/img/fullscreen.png
UcbCs294ShenduQianghuaXuexiZhongwenBijiXietian/img/loader.gif
UcbCs294ShenduQianghuaXuexiZhongwenBijiXietian/img/menu-icon.png
UcbCs294ShenduQianghuaXuexiZhongwenBijiXietian/img/save.png
UcbCs294ShenduQianghuaXuexiZhongwenBijiXietian/img/saved.png
UcbCs294ShenduQianghuaXuexiZhongwenBijiXietian/img/settings-s.png
UcbCs294ShenduQianghuaXuexiZhongwenBijiXietian/img/settings.png
UcbCs294ShenduQianghuaXuexiZhongwenBijiXietian/img/star.png
UcbCs294ShenduQianghuaXuexiZhongwenBijiXietian/js/__init__.py
UcbCs294ShenduQianghuaXuexiZhongwenBijiXietian/js/epub.js
ucb_cs294_shendu_qianghua_xuexi_zhongwen_biji_xietian-2024.3.4.0.dist-info/METADATA
ucb_cs294_shendu_qianghua_xuexi_zhongwen_biji_xietian-2024.3.4.0.dist-info/WHEEL
ucb_cs294_shendu_qianghua_xuexi_zhongwen_biji_xietian-2024.3.4.0.dist-info/entry_points.txt
ucb_cs294_shendu_qianghua_xuexi_zhongwen_biji_xietian-2024.3.4.0.dist-info/top_level.txt
ucb_cs294_shendu_qianghua_xuexi_zhongwen_biji_xietian-2024.3.4.0.dist-info/RECORD
